hdy_pypi_test.py
setup.py
hdy_pypi_test.egg-info/PKG-INFO
hdy_pypi_test.egg-info/SOURCES.txt
hdy_pypi_test.egg-info/dependency_links.txt
hdy_pypi_test.egg-info/entry_points.txt
hdy_pypi_test.egg-info/top_level.txt