Metadata-Version: 1.0
Name: hdy-pypi-test
Version: 1.1.0
Summary: test in Python.
Home-page: https://pypi.org/project/hdy-pypi-test/
Author: hdy
Author-email: 1015296415@qq.com
License: UNKNOWN
Platform: UNKNOWN
